forecast_ar/__init__.py
forecast_ar/forecast.py
forecast_ar/model_select.py
forecast_ar/utils/plotting.py
forecast_ar-0.0.1.dist-info/WHEEL
forecast_ar-0.0.1.dist-info/METADATA
forecast_ar-0.0.1.dist-info/LICENSE
forecast_ar-0.0.1.dist-info/RECORD
