Metadata-Version: 2.1
Name: forecast-ar
Version: 0.0.1
Summary: Automation of forecast models testing, combining and predicting
Home-page: https://github.com/amineraboun/forecast
Keywords: arima,ets,theta,tbats,prophet
Author: amineraboun
Author-email: amineraboun@gmail.com
Requires-Python: >=3.8,<3.12
Classifier: License :: OSI Approved :: MIT License
Classifier: Operating System :: OS Independent
Classifier: Programming Language :: Python :: 3
Classifier: Programming Language :: Python :: 3.8
Classifier: Programming Language :: Python :: 3.9
Classifier: Programming Language :: Python :: 3.10
Classifier: Programming Language :: Python :: 3.11
Classifier: Programming Language :: Python :: 3
Requires-Dist: matplotlib (>=3.7.2,<4.0.0)
Requires-Dist: nbsphinx (>=0.9.2,<0.10.0)
Requires-Dist: pandoc (>=2.3,<3.0)
Requires-Dist: prophet (>=1.1.4,<2.0.0)
Requires-Dist: seaborn (>=0.12.2,<0.13.0)
Requires-Dist: sktime (>=0.21.0,<0.22.0)
Requires-Dist: sphinx (>=7.1.2,<8.0.0)
Requires-Dist: sphinx-mdinclude (>=0.5.3,<0.6.0)
Requires-Dist: statsforecast (>=1.5.0,<2.0.0)
Requires-Dist: statsmodels (>=0.14.0,<0.15.0)
Requires-Dist: tbats (>=1.1.3,<2.0.0)
Requires-Dist: tqdm (>=4.66.0,<5.0.0)
Project-URL: Repository, https://github.com/amineraboun/forecast
